agnocomplete/__init__.py
agnocomplete/app.py
agnocomplete/constants.py
agnocomplete/core.py
agnocomplete/decorators.py
agnocomplete/exceptions.py
agnocomplete/fields.py
agnocomplete/forms.py
agnocomplete/register.py
agnocomplete/urls.py
agnocomplete/views.py
agnocomplete/widgets.py
django_agnocomplete-2.2.0.dist-info/LICENSE
django_agnocomplete-2.2.0.dist-info/METADATA
django_agnocomplete-2.2.0.dist-info/WHEEL
django_agnocomplete-2.2.0.dist-info/top_level.txt
django_agnocomplete-2.2.0.dist-info/zip-safe
django_agnocomplete-2.2.0.dist-info/RECORD
